odoo9_addon_document_page_environment_manual-9.0.1.0.0-py2.7-nspkg.pth
odoo9_addon_document_page_environment_manual-9.0.1.0.0.dist-info/top_level.txt
odoo9_addon_document_page_environment_manual-9.0.1.0.0.dist-info/WHEEL
odoo9_addon_document_page_environment_manual-9.0.1.0.0.dist-info/RECORD
odoo9_addon_document_page_environment_manual-9.0.1.0.0.dist-info/metadata.json
odoo9_addon_document_page_environment_manual-9.0.1.0.0.dist-info/DESCRIPTION.rst
odoo9_addon_document_page_environment_manual-9.0.1.0.0.dist-info/METADATA
odoo9_addon_document_page_environment_manual-9.0.1.0.0.dist-info/namespace_packages.txt
odoo_addons/document_page_environment_manual/__openerp__.py
odoo_addons/document_page_environment_manual/__init__.py
odoo_addons/document_page_environment_manual/README.rst
odoo_addons/document_page_environment_manual/migrations/7.0.1.0/pre-migration.py
odoo_addons/document_page_environment_manual/i18n/document_page_environment_manual.pot
odoo_addons/document_page_environment_manual/i18n/sl.po
odoo_addons/document_page_environment_manual/i18n/nb.po
odoo_addons/document_page_environment_manual/i18n/de.po
odoo_addons/document_page_environment_manual/i18n/vi.po
odoo_addons/document_page_environment_manual/i18n/fr.po
odoo_addons/document_page_environment_manual/i18n/pt_BR.po
odoo_addons/document_page_environment_manual/i18n/sv.po
odoo_addons/document_page_environment_manual/data/document_page_environment_manual.xml
odoo_addons/document_page_environment_manual/static/description/icon.png
